{
  "drivers": [
    {
      "name": "Alexander Albon",
      "number": 23,
      "team": "Williams",
      "years": {
        "2019": { "team": "Red Bull", "points": 16, "rank": 16 },
        "2020": { "team": "Red Bull", "points": 105, "rank": 4 },
        "2022": { "team": "Williams", "points": 4, "rank": 20 },
        "2023": { "team": "Williams", "points": 27, "rank": 16 },
        "2024": { "team": "Williams", "points": 12, "rank": 16 },
        "2025": { "team": "Williams", "points": 84, "rank": 8 },
        "2026": { "team": "Williams", "points": 0, "rank": 18 }
      }
    },
    {
      "name": "Fernando Alonso",
      "number": 14,
      "team": "Aston Martin",
      "years": {
        "2001": { "team": "Minardi", "points": 0, "rank": 24 },
        "2003": { "team": "Renault", "points": 55, "rank": 6 },
        "2004": { "team": "Renault", "points": 59, "rank": 4 },
        "2005": { "team": "Renault", "points": 133, "rank": 1 },
        "2006": { "team": "Renault", "points": 134, "rank": 1 },
        "2007": { "team": "McLaren", "points": 109, "rank": 3 },
        "2008": { "team": "Renault", "points": 61, "rank": 5 },
        "2009": { "team": "Renault", "points": 26, "rank": 9 },
        "2010": { "team": "Ferrari", "points": 252, "rank": 2 },
        "2011": { "team": "Ferrari", "points": 257, "rank": 4 },
        "2012": { "team": "Ferrari", "points": 278, "rank": 3 },
        "2013": { "team": "Ferrari", "points": 242, "rank": 2 },
        "2014": { "team": "Ferrari", "points": 161, "rank": 6 },
        "2015": { "team": "McLaren", "points": 11, "rank": 17 },
        "2016": { "team": "McLaren", "points": 54, "rank": 10 },
        "2017": { "team": "McLaren", "points": 26, "rank": 13 },
        "2018": { "team": "McLaren", "points": 50, "rank": 11 },
        "2021": { "team": "Alpine", "points": 81, "rank": 10 },
        "2022": { "team": "Alpine", "points": 71, "rank": 12 },
        "2023": { "team": "Aston Martin", "points": 206, "rank": 4 },
        "2024": { "team": "Aston Martin", "points": 84, "rank": 12 },
        "2025": { "team": "Aston Martin", "points": 56, "rank": 10 },
        "2026": { "team": "Aston Martin", "points": 0, "rank": 21 }
      }
    },
    {
      "name": "Kimi Antonelli",
      "number": 12,
      "team": "Mercedes",
      "years": {
        "2025": { "team": "Mercedes", "points": 23, "rank": 17 },
        "2026": { "team": "Mercedes", "points": 72, "rank": 1 }
      }
    },
    {
      "name": "Oliver Bearman",
      "number": 87,
      "team": "Haas",
      "years": {
        "2024": { "team": "Haas", "points": 7, "rank": 21 },
        "2025": { "team": "Haas", "points": 41, "rank": 13 },
        "2026": { "team": "Haas", "points": 17, "rank": 7 }
      }
    },
    {
      "name": "Gabriel Bortoleto",
      "number": 5,
      "team": "Audi",
      "years": {
        "2025": { "team": "Audi", "points": 19, "rank": 19 },
        "2026": { "team": "Audi", "points": 2, "rank": 13 }
      }
    },
    {
      "name": "Valtteri Bottas",
      "number": 77,
      "team": "Cadillac",
      "years": {
        "2013": { "team": "Williams", "points": 4, "rank": 17 },
        "2014": { "team": "Williams", "points": 85, "rank": 8 },
        "2015": { "team": "Williams", "points": 136, "rank": 5 },
        "2016": { "team": "Williams", "points": 85, "rank": 8 },
        "2017": { "team": "Mercedes", "points": 305, "rank": 3 },
        "2018": { "team": "Mercedes", "points": 247, "rank": 5 },
        "2019": { "team": "Mercedes", "points": 326, "rank": 2 },
        "2020": { "team": "Mercedes", "points": 223, "rank": 2 },
        "2021": { "team": "Mercedes", "points": 226, "rank": 3 },
        "2022": { "team": "Sauber", "points": 49, "rank": 10 },
        "2023": { "team": "Sauber", "points": 10, "rank": 15 },
        "2024": { "team": "Sauber", "points": 0, "rank": 22 },
        "2026": { "team": "Cadillac", "points": 0, "rank": 19 }
      }
    },
    {
      "name": "Franco Colapinto",
      "number": 43,
      "team": "Alpine",
      "years": {
        "2024": { "team": "Williams", "points": 5, "rank": 19 },
        "2025": { "team": "Alpine", "points": 0, "rank": 21 },
        "2026": { "team": "Alpine", "points": 1, "rank": 16 }
      }
    },
    {
      "name": "Pierre Gasly",
      "number": 10,
      "team": "Alpine",
      "years": {
        "2017": { "team": "Toro Rosso", "points": 12, "rank": 13 },
        "2018": { "team": "Toro Rosso", "points": 29, "rank": 11 },
        "2019": { "team": "Red Bull", "points": 95, "rank": 7 },
        "2020": { "team": "AlphaTauri", "points": 75, "rank": 9 },
        "2021": { "team": "AlphaTauri", "points": 110, "rank": 9 },
        "2022": { "team": "AlphaTauri", "points": 98, "rank": 10 },
        "2023": { "team": "Alpine", "points": 25, "rank": 13 },
        "2024": { "team": "Alpine", "points": 34, "rank": 10 },
        "2025": { "team": "Alpine", "points": 22, "rank": 16 },
        "2026": { "team": "Alpine", "points": 15, "rank": 8 }
      }
    },
    {
      "name": "Isack Hadjar",
      "number": 6,
      "team": "Red Bull",
      "years": {
        "2025": { "team": "Racing Bulls", "points": 92, "rank": 6 },
        "2026": { "team": "Red Bull", "points": 4, "rank": 12 }
      }
    },
    {
      "name": "Lewis Hamilton",
      "number": 44,
      "team": "Ferrari",
      "years": {
        "2007": { "team": "McLaren", "points": 109, "rank": 2 },
        "2008": { "team": "McLaren", "points": 98, "rank": 1 },
        "2009": { "team": "McLaren", "points": 49, "rank": 5 },
        "2010": { "team": "McLaren", "points": 240, "rank": 4 },
        "2011": { "team": "McLaren", "points": 227, "rank": 5 },
        "2012": { "team": "McLaren", "points": 190, "rank": 4 },
        "2013": { "team": "Mercedes", "points": 189, "rank": 4 },
        "2014": { "team": "Mercedes", "points": 384, "rank": 1 },
        "2015": { "team": "Mercedes", "points": 381, "rank": 1 },
        "2016": { "team": "Mercedes", "points": 380, "rank": 2 },
        "2017": { "team": "Mercedes", "points": 363, "rank": 1 },
        "2018": { "team": "Mercedes", "points": 358, "rank": 1 },
        "2019": { "team": "Mercedes", "points": 413, "rank": 1 },
        "2020": { "team": "Mercedes", "points": 347, "rank": 1 },
        "2021": { "team": "Mercedes", "points": 387.5, "rank": 2 },
        "2022": { "team": "Mercedes", "points": 240, "rank": 6 },
        "2023": { "team": "Mercedes", "points": 234, "rank": 3 },
        "2024": { "team": "Mercedes", "points": 233, "rank": 7 },
        "2025": { "team": "Ferrari", "points": 156, "rank": 6 },
        "2026": { "team": "Ferrari", "points": 41, "rank": 4 }
      }
    },
    {
      "name": "Nico Hülkenberg",
      "number": 27,
      "team": "Audi",
      "years": {
        "2010": { "team": "Williams", "points": 17, "rank": 14 },
        "2012": { "team": "Force India", "points": 63, "rank": 11 },
        "2013": { "team": "Force India", "points": 43, "rank": 10 },
        "2014": { "team": "Force India", "points": 59, "rank": 9 },
        "2015": { "team": "Force India", "points": 78, "rank": 9 },
        "2016": { "team": "Force India", "points": 72, "rank": 9 },
        "2017": { "team": "Renault", "points": 43, "rank": 10 },
        "2018": { "team": "Renault", "points": 69, "rank": 7 },
        "2019": { "team": "Renault", "points": 37, "rank": 14 },
        "2020": { "team": "Racing Point", "points": 3, "rank": 19 },
        "2022": { "team": "Aston Martin", "points": 0, "rank": 22 },
        "2023": { "team": "Haas", "points": 27, "rank": 14 },
        "2024": { "team": "Haas", "points": 41, "rank": 11 },
        "2025": { "team": "Audi", "points": 51, "rank": 11 },
        "2026": { "team": "Audi", "points": 0, "rank": 17 }
      }
    },
    {
      "name": "Liam Lawson",
      "number": 30,
      "team": "Racing Bulls",
      "years": {
        "2023": { "team": "Racing Bulls", "points": 4, "rank": 21 },
        "2024": { "team": "Racing Bulls", "points": 38, "rank": 14 },
        "2025": { "team": "Red Bull", "points": 46, "rank": 12 },
        "2026": { "team": "Racing Bulls", "points": 10, "rank": 10 }
      }
    },
    {
      "name": "Charles Leclerc",
      "number": 16,
      "team": "Ferrari",
      "years": {
        "2018": { "team": "Sauber", "points": 39, "rank": 13 },
        "2019": { "team": "Ferrari", "points": 264, "rank": 4 },
        "2020": { "team": "Ferrari", "points": 202, "rank": 8 },
        "2021": { "team": "Ferrari", "points": 159, "rank": 7 },
        "2022": { "team": "Ferrari", "points": 308, "rank": 2 },
        "2023": { "team": "Ferrari", "points": 206, "rank": 5 },
        "2024": { "team": "Ferrari", "points": 356, "rank": 3 },
        "2025": { "team": "Ferrari", "points": 242, "rank": 5 },
        "2026": { "team": "Ferrari", "points": 49, "rank": 3 }
      }
    },
    {
      "name": "Arvid Lindblad",
      "number": 41,
      "team": "Racing Bulls",
      "years": {
        "2026": { "team": "Racing Bulls", "points": 4, "rank": 11 }
      }
    },
    {
      "name": "Lando Norris",
      "number": 1,
      "team": "McLaren",
      "years": {
        "2019": { "team": "McLaren", "points": 49, "rank": 11 },
        "2020": { "team": "McLaren", "points": 97, "rank": 7 },
        "2021": { "team": "McLaren", "points": 160, "rank": 6 },
        "2022": { "team": "McLaren", "points": 122, "rank": 7 },
        "2023": { "team": "McLaren", "points": 205, "rank": 6 },
        "2024": { "team": "McLaren", "points": 374, "rank": 2 },
        "2025": { "team": "McLaren", "points": 567, "rank": 1 },
        "2026": { "team": "McLaren", "points": 25, "rank": 5 }
      }
    },
    {
      "name": "Esteban Ocon",
      "number": 31,
      "team": "Haas",
      "years": {
        "2016": { "team": "Manor", "points": 9, "rank": 20 },
        "2017": { "team": "Force India", "points": 20, "rank": 15 },
        "2018": { "team": "Force India", "points": 21, "rank": 12 },
        "2020": { "team": "Renault", "points": 17, "rank": 12 },
        "2021": { "team": "Alpine", "points": 74, "rank": 7 },
        "2022": { "team": "Alpine", "points": 92, "rank": 8 },
        "2023": { "team": "Alpine", "points": 58, "rank": 12 },
        "2024": { "team": "Alpine", "points": 23, "rank": 14 },
        "2025": { "team": "Haas", "points": 38, "rank": 15 },
        "2026": { "team": "Haas", "points": 1, "rank": 15 }
      }
    },
    {
      "name": "Sergio Pérez",
      "number": 11,
      "team": "Cadillac",
      "years": {
        "2011": { "team": "Sauber", "points": 20, "rank": 10 },
        "2012": { "team": "Sauber", "points": 66, "rank": 10 },
        "2013": { "team": "McLaren", "points": 59, "rank": 10 },
        "2014": { "team": "Force India", "points": 78, "rank": 9 },
        "2015": { "team": "Force India", "points": 78, "rank": 9 },
        "2016": { "team": "Force India", "points": 101, "rank": 7 },
        "2017": { "team": "Force India", "points": 100, "rank": 7 },
        "2018": { "team": "Racing Point", "points": 22, "rank": 11 },
        "2019": { "team": "Racing Point", "points": 23, "rank": 13 },
        "2020": { "team": "Racing Point", "points": 125, "rank": 4 },
        "2021": { "team": "Red Bull", "points": 190, "rank": 4 },
        "2022": { "team": "Red Bull", "points": 305, "rank": 3 },
        "2023": { "team": "Red Bull", "points": 285, "rank": 2 },
        "2024": { "team": "Red Bull", "points": 152, "rank": 8 },
        "2026": { "team": "Cadillac", "points": 0, "rank": 20 }
      }
    },
    {
      "name": "Oscar Piastri",
      "number": 81,
      "team": "McLaren",
      "years": {
        "2023": { "team": "McLaren", "points": 97, "rank": 8 },
        "2024": { "team": "McLaren", "points": 292, "rank": 4 },
        "2025": { "team": "McLaren", "points": 562, "rank": 3 },
        "2026": { "team": "McLaren", "points": 21, "rank": 6 }
      }
    },
    {
      "name": "George Russell",
      "number": 63,
      "team": "Mercedes",
      "years": {
        "2019": { "team": "Williams", "points": 0, "rank": 20 },
        "2020": { "team": "Williams", "points": 3, "rank": 18 },
        "2021": { "team": "Williams", "points": 16, "rank": 15 },
        "2022": { "team": "Mercedes", "points": 275, "rank": 4 },
        "2023": { "team": "Mercedes", "points": 175, "rank": 8 },
        "2024": { "team": "Mercedes", "points": 245, "rank": 6 },
        "2025": { "team": "Mercedes", "points": 319, "rank": 4 },
        "2026": { "team": "Mercedes", "points": 63, "rank": 2 }
      }
    },
    {
      "name": "Carlos Sainz",
      "number": 55,
      "team": "Williams",
      "years": {
        "2015": { "team": "Toro Rosso", "points": 18, "rank": 13 },
        "2016": { "team": "Toro Rosso", "points": 26, "rank": 13 },
        "2017": { "team": "Renault", "points": 54, "rank": 9 },
        "2018": { "team": "Renault", "points": 57, "rank": 9 },
        "2019": { "team": "McLaren", "points": 96, "rank": 6 },
        "2020": { "team": "McLaren", "points": 105, "rank": 6 },
        "2021": { "team": "Ferrari", "points": 164.5, "rank": 5 },
        "2022": { "team": "Ferrari", "points": 246, "rank": 5 },
        "2023": { "team": "Ferrari", "points": 200, "rank": 7 },
        "2024": { "team": "Ferrari", "points": 290, "rank": 5 },
        "2025": { "team": "Williams", "points": 27, "rank": 14 },
        "2026": { "team": "Williams", "points": 2, "rank": 14 }
      }
    },
    {
      "name": "Lance Stroll",
      "number": 18,
      "team": "Aston Martin",
      "years": {
        "2017": { "team": "Williams", "points": 40, "rank": 12 },
        "2018": { "team": "Williams", "points": 6, "rank": 18 },
        "2019": { "team": "Racing Point", "points": 43, "rank": 11 },
        "2020": { "team": "Racing Point", "points": 75, "rank": 8 },
        "2021": { "team": "Aston Martin", "points": 34, "rank": 13 },
        "2022": { "team": "Aston Martin", "points": 24, "rank": 14 },
        "2023": { "team": "Aston Martin", "points": 46, "rank": 10 },
        "2024": { "team": "Aston Martin", "points": 16, "rank": 17 },
        "2025": { "team": "Aston Martin", "points": 24, "rank": 18 },
        "2026": { "team": "Aston Martin", "points": 0, "rank": 22 }
      }
    },
    {
      "name": "Max Verstappen",
      "number": 3,
      "team": "Red Bull",
      "years": {
        "2015": { "team": "Toro Rosso", "points": 49, "rank": 12 },
        "2016": { "team": "Red Bull", "points": 204, "rank": 5 },
        "2017": { "team": "Red Bull", "points": 270, "rank": 6 },
        "2018": { "team": "Red Bull", "points": 249, "rank": 3 },
        "2019": { "team": "Red Bull", "points": 278, "rank": 3 },
        "2020": { "team": "Red Bull", "points": 214, "rank": 3 },
        "2021": { "team": "Red Bull", "points": 395.5, "rank": 1 },
        "2022": { "team": "Red Bull", "points": 454, "rank": 1 },
        "2023": { "team": "Red Bull", "points": 575, "rank": 1 },
        "2024": { "team": "Red Bull", "points": 437, "rank": 1 },
        "2025": { "team": "Red Bull", "points": 565, "rank": 2 },
        "2026": { "team": "Red Bull", "points": 12, "rank": 9 }
      }
    }
  ],
  "teams": [
    { "name": "Alpine", "fullName": "Alpine F1 Team", "drivers": ["Franco Colapinto", "Pierre Gasly"] },
    { "name": "Aston Martin", "fullName": "Aston Martin Aramco F1 Team", "drivers": ["Fernando Alonso", "Lance Stroll"] },
    { "name": "Audi", "fullName": "Audi Revolut F1 Team", "drivers": ["Gabriel Bortoleto", "Nico Hülkenberg"] },
    { "name": "Cadillac", "fullName": "Cadillac Formula 1 Team", "drivers": ["Valtteri Bottas", "Sergio Pérez"] },
    { "name": "Ferrari", "fullName": "Scuderia Ferrari HP", "drivers": ["Lewis Hamilton", "Charles Leclerc"] },
    { "name": "Haas", "fullName": "Haas F1 Team", "drivers": ["Oliver Bearman", "Esteban Ocon"] },
    { "name": "McLaren", "fullName": "McLaren Mastercard F1 Team", "drivers": ["Lando Norris", "Oscar Piastri"] },
    { "name": "Mercedes", "fullName": "Mercedes-AMG Petronas F1 Team", "drivers": ["Kimi Antonelli", "George Russell"] },
    { "name": "Racing Bulls", "fullName": "Racing Bulls F1 Team", "drivers": ["Liam Lawson", "Arvid Lindblad"] },
    { "name": "Red Bull", "fullName": "Red Bull Racing", "drivers": ["Isack Hadjar", "Max Verstappen"] },
    { "name": "Williams", "fullName": "Atlassian Williams F1 Team", "drivers": ["Alexander Albon", "Carlos Sainz"] }
  ],
  "events": [
    { "round": 1, "name": "Australian Grand Prix", "circuit": "Albert Park Circuit", "location": "Melbourne, Australia", "date": "2026-03-08", "result": ["Russell", "Antonelli", "Leclerc", "Hamilton", "Norris", "Verstappen", "Bearman", "Lindblad", "Bortoleto", "Gasly", "Ocon", "Albon", "Lawson", "Colapinto", "Sainz", "Pérez"] },
    { "round": 2, "name": "Chinese Grand Prix", "circuit": "Shanghai International Circuit", "location": "Shanghai, China", "date": "2026-03-15", "result": ["Antonelli", "Russell", "Hamilton", "Leclerc", "Bearman", "Gasly", "Lawson", "Hadjar", "Sainz", "Colapinto", "Hülkenberg", "Lindblad", "Bottas", "Ocon", "Pérez"] },
    { "round": 3, "name": "Japanese Grand Prix", "circuit": "Suzuka International Racing Course", "location": "Suzuka, Japan", "date": "2026-03-29", "result": ["Antonelli", "Piastri", "Leclerc", "Russell", "Norris", "Hamilton", "Gasly", "Verstappen", "Lawson", "Ocon", "Hülkenberg", "Hadjar", "Bortoleto", "Lindblad", "Sainz", "Colapinto", "Pérez", "Alonso", "Bottas", "Albon"] },
    { "round": 4, "name": "Miami Grand Prix", "circuit": "Miami International Autodrome", "location": "Miami, USA", "date": "2026-05-03" },
    { "round": 5, "name": "Canadian Grand Prix", "circuit": "Circuit Gilles Villeneuve", "location": "Montreal, Canada", "date": "2026-05-24" },
    { "round": 6, "name": "Monaco Grand Prix", "circuit": "Circuit de Monaco", "location": "Monaco", "date": "2026-06-07" },
    { "round": 7, "name": "Spanish Grand Prix", "circuit": "Circuit de Barcelona-Catalunya", "location": "Barcelona, Spain", "date": "2026-06-14" },
    { "round": 8, "name": "Austrian Grand Prix", "circuit": "Red Bull Ring", "location": "Spielberg, Austria", "date": "2026-06-28" },
    { "round": 9, "name": "British Grand Prix", "circuit": "Silverstone Circuit", "location": "Silverstone, UK", "date": "2026-07-05" },
    { "round": 10, "name": "Belgian Grand Prix", "circuit": "Circuit de Spa-Francorchamps", "location": "Spa, Belgium", "date": "2026-07-19" },
    { "round": 11, "name": "Hungarian Grand Prix", "circuit": "Hungaroring", "location": "Budapest, Hungary", "date": "2026-07-26" },
    { "round": 12, "name": "Dutch Grand Prix", "circuit": "Circuit Zandvoort", "location": "Zandvoort, Netherlands", "date": "2026-08-23" },
    { "round": 13, "name": "Italian Grand Prix", "circuit": "Autodromo Nazionale Monza", "location": "Monza, Italy", "date": "2026-09-06" },
    { "round": 14, "name": "Madrid Grand Prix", "circuit": "Madrid Street Circuit", "location": "Madrid, Spain", "date": "2026-09-13" },
    { "round": 15, "name": "Azerbaijan Grand Prix", "circuit": "Baku City Circuit", "location": "Baku, Azerbaijan", "date": "2026-09-26" },
    { "round": 16, "name": "Singapore Grand Prix", "circuit": "Marina Bay Street Circuit", "location": "Singapore", "date": "2026-10-11" },
    { "round": 17, "name": "United States Grand Prix", "circuit": "Circuit of the Americas", "location": "Austin, USA", "date": "2026-10-25" },
    { "round": 18, "name": "Mexico City Grand Prix", "circuit": "Autodromo Hermanos Rodriguez", "location": "Mexico City, Mexico", "date": "2026-11-01" },
    { "round": 19, "name": "São Paulo Grand Prix", "circuit": "Autodromo Jose Carlos Pace", "location": "São Paulo, Brazil", "date": "2026-11-08" },
    { "round": 20, "name": "Las Vegas Grand Prix", "circuit": "Las Vegas Strip Circuit", "location": "Las Vegas, USA", "date": "2026-11-21" },
    { "round": 21, "name": "Qatar Grand Prix", "circuit": "Lusail International Circuit", "location": "Lusail, Qatar", "date": "2026-11-29" },
    { "round": 22, "name": "Abu Dhabi Grand Prix", "circuit": "Yas Marina Circuit", "location": "Abu Dhabi, UAE", "date": "2026-12-06" }
  ]
}
